CHANGES.txt
LICENSE
MANIFEST.in
README.md
setup.py
petitioners/__init__.py
petitioners.egg-info/PKG-INFO
petitioners.egg-info/SOURCES.txt
petitioners.egg-info/dependency_links.txt
petitioners.egg-info/not-zip-safe
petitioners.egg-info/requires.txt
petitioners.egg-info/top_level.txt