Metadata-Version: 1.1
Name: petitioners
Version: 0.0.6
Summary: auditable tracing for linking requests between services
Home-page: UNKNOWN
Author: Balanced
Author-email: dev+petitioners@balancedpayments.com
License: The MIT License: http://www.opensource.org/licenses/mit-license.php
Platform: UNKNOWN
Classifier: Programming Language :: Python
Classifier: License :: OSI Approved :: MIT License
